beehiiv_server.py
mseep_beehiiv_mcp_server-0.1.1.dist-info/METADATA
mseep_beehiiv_mcp_server-0.1.1.dist-info/WHEEL
mseep_beehiiv_mcp_server-0.1.1.dist-info/top_level.txt
mseep_beehiiv_mcp_server-0.1.1.dist-info/RECORD
