Metadata-Version: 2.4
Name: mseep-beehiiv-mcp-server
Version: 0.1.1
Summary: Add your description here
Author-email: mseep <support@skydeck.ai>
Requires-Python: >=3.11
Requires-Dist: mcp[cli]>=1.6.0
